{
  "total_documents": 70180,
  "documents_with_names": 51048,
  "unique_names": 123446,
  "total_mentions": 309552,
  "graph_nodes": 197237,
  "graph_edges": 7501065,
  "top_names": [
    [
      "Καίσαρος",
      4080
    ],
    [
      "Αὐρήλιος",
      1625
    ],
    [
      "Πτολεμαίου",
      1513
    ],
    [
      "Σεβαστοῦ",
      1499
    ],
    [
      "Αὐρηλίου",
      1319
    ],
    [
      "Σαραπίωνος",
      1023
    ],
    [
      "Αὐτοκράτορος Καίσαρος Μάρκου",
      875
    ],
    [
      "Καρανίδος",
      854
    ],
    [
      "Χάρακος",
      804
    ],
    [
      "Αἰλίου",
      788
    ],
    [
      "Διονυσίου",
      774
    ],
    [
      "Ζήνωνι",
      739
    ],
    [
      "Demotic",
      729
    ],
    [
      "Σαραπίων",
      721
    ],
    [
      "Αὐτοκράτορος Καίσαρος Τίτου",
      681
    ],
    [
      "Πολέμωνος",
      680
    ],
    [
      "Τραιανοῦ",
      648
    ],
    [
      "Πτολεμαῖος",
      629
    ],
    [
      "Μηνᾶ",
      627
    ],
    [
      "Θέωνος",
      620
    ],
    [
      "Αὐρηλίῳ",
      598
    ],
    [
      "Σεβαστῶν",
      575
    ],
    [
      "Σεβαστοῦ Γερμανικοῦ Αὐτοκράτορος",
      568
    ],
    [
      "Διδύμου",
      566
    ],
    [
      "Φοιβάμμωνος",
      543
    ],
    [
      "Αὐτοκράτορος Καίσαρος Τραιανοῦ",
      518
    ],
    [
      "Θεμίστου",
      517
    ],
    [
      "Σοκνοπαίου Νήσου",
      516
    ],
    [
      "Αὐγούστου",
      493
    ],
    [
      "Θεοδώρου",
      489
    ],
    [
      "Διοσκόρου",
      487
    ],
    [
      "Σεβαστοῦ Εὐσεβοῦς",
      462
    ],
    [
      "Διονύσιος",
      451
    ],
    [
      "Διὸς",
      449
    ],
    [
      "Μάρκου Αὐρηλίου",
      440
    ],
    [
      "Δημητρίου",
      434
    ],
    [
      "Τιβερίου Καίσαρος Σεβαστοῦ",
      425
    ],
    [
      "Νότου",
      413
    ],
    [
      "Εὐσεβοῦς Εὐτυχοῦς Σεβαστοῦ",
      407
    ],
    [
      "Τιβερίου Κλαυδίου Καίσαρος",
      395
    ],
    [
      "Πτολεμαίωι",
      384
    ],
    [
      "Σαραπίωνι",
      369
    ],
    [
      "Οὐήρου",
      363
    ],
    [
      "Φλαουίου",
      355
    ],
    [
      "Γεωργίου",
      345
    ],
    [
      "Πετεσούχου",
      344
    ],
    [
      "Σερήνου",
      341
    ],
    [
      "Αὐτοκράτορος",
      340
    ],
    [
      "Αὐτοκράτορος Καίσαρος Νέρουα",
      338
    ],
    [
      "Παύλου",
      333
    ],
    [
      "Κολλούθου",
      331
    ],
    [
      "Χαιρήμονος",
      324
    ],
    [
      "Θέων",
      323
    ],
    [
      "Διόσκορος",
      298
    ],
    [
      "Τραιανοῦ Σεβαστοῦ Γερμανικοῦ",
      297
    ],
    [
      "Αἰγύπτου",
      293
    ],
    [
      "Χοίαχ",
      288
    ],
    [
      "Βίκτορος",
      287
    ],
    [
      "Αὐρηλίων",
      285
    ],
    [
      "Διογένους",
      285
    ],
    [
      "Χριστοῦ",
      285
    ],
    [
      "Νείλου",
      282
    ],
    [
      "Δίδυμος",
      280
    ],
    [
      "Λουκίου Σεπτιμίου Σεουήρου",
      279
    ],
    [
      "Δομιτιανοῦ",
      277
    ],
    [
      "Σερῆνος",
      275
    ],
    [
      "Θηβαίδος",
      273
    ],
    [
      "Θεῷ",
      266
    ],
    [
      "Μάρκου",
      265
    ],
    [
      "Τραιανοῦ Καίσαρος",
      262
    ],
    [
      "Αὐρηλίου Σεουήρου",
      256
    ],
    [
      "Σαταβοῦτος",
      255
    ],
    [
      "Ζωίλου",
      249
    ],
    [
      "Πέτρου",
      249
    ],
    [
      "Σοήνης",
      248
    ],
    [
      "Κάστορος",
      247
    ],
    [
      "Φοιβάμμων",
      247
    ],
    [
      "Μάρωνος",
      246
    ],
    [
      "Κωνσταντίου",
      246
    ],
    [
      "Διοκλητιανοῦ",
      245
    ],
    [
      "Πετεσοῦχος",
      244
    ],
    [
      "Πετοσίριος",
      242
    ],
    [
      "Θαήσιος",
      238
    ],
    [
      "Θεόδωρος",
      237
    ],
    [
      "Θέωνι",
      236
    ],
    [
      "Νήσου",
      235
    ],
    [
      "Αὐτοκράτορος Καίσαρος Δομιτιανοῦ",
      232
    ],
    [
      "Θεαδελφείας",
      232
    ],
    [
      "Δημήτριος",
      232
    ],
    [
      "Οὐεσπασιανοῦ",
      225
    ],
    [
      "Κομμόδου",
      225
    ],
    [
      "Κροκοδίλων",
      224
    ],
    [
      "Αὐρήλιοι",
      224
    ],
    [
      "Μεχὶρ",
      221
    ],
    [
      "Δίου",
      220
    ],
    [
      "Μάρκου Αὐρηλίου Σεουήρου",
      219
    ],
    [
      "Χαιρήμων",
      217
    ],
    [
      "Αὐρηλίου Κομμόδου",
      215
    ],
    [
      "Αὐτοκράτορος Καίσαρος Λουκίου",
      214
    ],
    [
      "Μεμνονείων",
      214
    ],
    [
      "Μαρίας",
      212
    ],
    [
      "Εὐδαίμονος",
      210
    ],
    [
      "Εὐεργετῶν",
      210
    ],
    [
      "Χοιὰχ",
      208
    ],
    [
      "Νέρωνος Κλαυδίου Καίσαρος",
      207
    ],
    [
      "Μηνᾶς",
      204
    ],
    [
      "Φλαυίου",
      203
    ],
    [
      "Καισαρείου",
      202
    ],
    [
      "Σεβαστοῦ Γερμανικοῦ",
      202
    ],
    [
      "Μαξιμιανοῦ",
      201
    ],
    [
      "Κερκεσούχων",
      198
    ],
    [
      "Κρονίωνος",
      196
    ],
    [
      "Φιλαδέλφου",
      196
    ],
    [
      "Στοτοήτιος",
      194
    ],
    [
      "Καισάρων",
      194
    ],
    [
      "Κλεοπάτρας",
      193
    ],
    [
      "Πανίσκου",
      189
    ],
    [
      "Πτολεμαίδος",
      188
    ],
    [
      "Φιλοξένου",
      187
    ],
    [
      "Κάστωρ",
      186
    ],
    [
      "Διονυσίωι",
      186
    ],
    [
      "Βακχιάδος",
      186
    ],
    [
      "Σεουήρου",
      184
    ],
    [
      "Φιλαδελφείας",
      183
    ],
    [
      "Βίκτωρ",
      181
    ],
    [
      "Φλαουίῳ",
      179
    ],
    [
      "Πτολεμαῖον",
      178
    ],
    [
      "Μύσθου",
      178
    ],
    [
      "Θεοδοσίου",
      177
    ],
    [
      "Παῦλος",
      176
    ],
    [
      "Στεφάνου",
      176
    ],
    [
      "Τεβτύνεως",
      176
    ],
    [
      "Μέμφιν",
      174
    ],
    [
      "Κοσμᾶ",
      173
    ],
    [
      "Σαρα",
      172
    ],
    [
      "Τεπτύνεως",
      169
    ],
    [
      "Μαξιμιανοῦ Σεβαστῶν",
      167
    ],
    [
      "Πνεφερῶτος",
      167
    ],
    [
      "Νέρωνος",
      167
    ],
    [
      "Πετε",
      166
    ],
    [
      "Δακικοῦ",
      165
    ],
    [
      "Διογένης",
      165
    ],
    [
      "Εὐσεβοῦς Σεβαστῶν",
      163
    ],
    [
      "Γαίου",
      160
    ],
    [
      "Φιλίππου",
      159
    ],
    [
      "Φίλωνος",
      158
    ],
    [
      "Κύρου",
      158
    ],
    [
      "Βερενίκης",
      157
    ],
    [
      "Μάρκου Αὐρηλίου Κομμόδου",
      157
    ],
    [
      "Θεοῦ",
      156
    ],
    [
      "Κωνσταντίνου",
      156
    ],
    [
      "Φιλοπατόρων",
      155
    ],
    [
      "Φαρμουθι",
      155
    ],
    [
      "Αὐγούστου Αὐτοκράτορος",
      155
    ],
    [
      "Αὐρηλία",
      154
    ],
    [
      "Θῶυθ",
      154
    ],
    [
      "Arabic",
      154
    ],
    [
      "Διοδώρου",
      154
    ],
    [
      "Παμώνθης",
      152
    ],
    [
      "Στοτοῆτις",
      151
    ],
    [
      "Σύρου",
      150
    ],
    [
      "Μέλας",
      150
    ],
    [
      "Μέμφεως",
      150
    ],
    [
      "Νέου Σεβαστοῦ",
      149
    ],
    [
      "Σοκνοπαίου",
      149
    ],
    [
      "Θωὺθ",
      148
    ],
    [
      "Πέρσης",
      148
    ],
    [
      "Βομπαή",
      148
    ],
    [
      "Γερμανικοῦ",
      147
    ],
    [
      "Παπνουθίου",
      147
    ],
    [
      "Πασίωνος",
      147
    ],
    [
      "Μακαρίου",
      147
    ],
    [
      "Νεῖλος",
      147
    ],
    [
      "Πουβλίου Σεπτιμίου Γέτα",
      146
    ],
    [
      "Αὐγούστων",
      145
    ],
    [
      "Ψεναμούνιος",
      145
    ],
    [
      "Πικῶς",
      145
    ],
    [
      "Τεῶτος",
      143
    ],
    [
      "Γάιος",
      142
    ],
    [
      "Εὐσεβοῦς Περτίνακος",
      142
    ],
    [
      "Γεώργιος",
      141
    ],
    [
      "Στοτοήτεως",
      139
    ],
    [
      "Θεοδώρῳ",
      139
    ],
    [
      "Μέλανος",
      139
    ],
    [
      "Εὐδαίμων",
      138
    ],
    [
      "Σαμβᾶ",
      138
    ],
    [
      "Πανίσκος",
      138
    ],
    [
      "Πετοσῖρις",
      137
    ],
    [
      "Τρύφωνος",
      136
    ],
    [
      "Πτολε",
      136
    ],
    [
      "Διονυσιάδος",
      136
    ],
    [
      "Παχὼνς",
      135
    ],
    [
      "Θεαδελφίας",
      135
    ],
    [
      "Καίσαρος Σεβαστοῦ",
      134
    ],
    [
      "Σεν",
      134
    ],
    [
      "Ζήνωνος",
      134
    ],
    [
      "Διδύμης",
      132
    ],
    [
      "Σαράπιδος",
      131
    ],
    [
      "Διονυσίῳ",
      131
    ],
    [
      "Αὐρηλίου Οὐήρου Σεβαστοῦ",
      129
    ],
    [
      "Κλαυδίου",
      129
    ],
    [
      "Μέμφει",
      129
    ],
    [
      "Πεκῦσις",
      129
    ],
    [
      "Πεκύσιος",
      128
    ],
    [
      "Φιλοπάτορος",
      127
    ],
    [
      "Διο",
      127
    ],
    [
      "Σερήνῳ",
      126
    ],
    [
      "Πτο",
      126
    ],
    [
      "Φιλαδελφίας",
      126
    ],
    [
      "Σαραπάμμων",
      125
    ],
    [
      "Πτολεμαίῳ",
      125
    ],
    [
      "Λυσιμάχου",
      125
    ],
    [
      "Ταυρίνου",
      125
    ],
    [
      "Λιβὸς",
      124
    ],
    [
      "Δημητρίωι",
      122
    ],
    [
      "Ψεν",
      121
    ],
    [
      "Σαραπίωνα",
      121
    ],
    [
      "Παρθικοῦ",
      121
    ],
    [
      "Πτολ",
      119
    ],
    [
      "Περτίνακος",
      118
    ],
    [
      "Σισόιτος",
      118
    ],
    [
      "Σαραπιάδος",
      117
    ],
    [
      "Παποντῶτος",
      117
    ],
    [
      "Δωρίωνος",
      116
    ],
    [
      "Σιλβανοῦ",
      116
    ],
    [
      "Αὐτοκράτορος Καίσαρος Γαίου",
      115
    ],
    [
      "Παμώνθου",
      115
    ],
    [
      "Πάσιτος",
      115
    ],
    [
      "Παθύρει",
      114
    ],
    [
      "Σύρος",
      114
    ],
    [
      "Κολλοῦθος",
      114
    ],
    [
      "Μουσαίου",
      114
    ],
    [
      "Πέτρος",
      114
    ],
    [
      "Ψάις",
      113
    ],
    [
      "Φοιβάμμωνι",
      113
    ],
    [
      "Αὐρήλιον",
      112
    ],
    [
      "Διονύσιον",
      112
    ],
    [
      "Αὐρηλίας",
      111
    ],
    [
      "Σύρων",
      111
    ],
    [
      "Σαραπάμμωνος",
      110
    ],
    [
      "Αὐτοκράτορος Καίσαρος Οὐεσπασιανοῦ",
      110
    ],
    [
      "Σωκράτης",
      109
    ],
    [
      "Πεθέως",
      108
    ],
    [
      "Περιτίου",
      108
    ],
    [
      "Λεωνίδου",
      108
    ],
    [
      "Γορπιαίου",
      108
    ],
    [
      "Σωτηρίχου",
      106
    ],
    [
      "Σωτήρων",
      106
    ],
    [
      "Δαισίου",
      106
    ],
    [
      "Σεπτιμίου Σεουήρου Εὐσεβοῦς",
      105
    ],
    [
      "Μαξίμου",
      105
    ],
    [
      "Ζωίλος",
      105
    ],
    [
      "Πτολεμαίδι Εὐεργέτιδι",
      103
    ],
    [
      "Δωροθέου",
      103
    ],
    [
      "Μάρων",
      102
    ],
    [
      "Σαραπ",
      102
    ],
    [
      "Σαταβοῦς",
      101
    ],
    [
      "Σαβείνου",
      101
    ],
    [
      "Θώθ",
      101
    ],
    [
      "Φαμενωθ",
      101
    ],
    [
      "Οὐαλεντινιανοῦ",
      99
    ],
    [
      "Σώτας",
      99
    ],
    [
      "Θηβαΐδος",
      98
    ],
    [
      "Πανὸς",
      98
    ],
    [
      "Πασίων",
      98
    ],
    [
      "Δύστρου",
      98
    ],
    [
      "Σωκράτους",
      97
    ],
    [
      "Σενουθίου",
      97
    ],
    [
      "Πνεφερῶς",
      97
    ],
    [
      "Πτολεμαίδι",
      96
    ],
    [
      "Σούχου",
      96
    ],
    [
      "Διοσκουρίδου",
      96
    ],
    [
      "Νικάνορος",
      96
    ],
    [
      "Οὐάλεντος",
      95
    ],
    [
      "Οὐαλερίου",
      95
    ],
    [
      "Μακάριος",
      95
    ],
    [
      "Θωθ",
      95
    ],
    [
      "Πᾶσις",
      95
    ],
    [
      "Καρανίδι",
      93
    ],
    [
      "Λουκίου",
      93
    ],
    [
      "Διδύμῳ",
      93
    ],
    [
      "Φιλαδέλφειαν",
      93
    ],
    [
      "Αὐτοκρατόρων Καισάρων Λουκίου",
      92
    ],
    [
      "Ψεναμοῦνις",
      92
    ],
    [
      "Διοφάνει",
      91
    ],
    [
      "Δαίμονος",
      91
    ],
    [
      "Μηνᾷ",
      91
    ],
    [
      "Φιλαδελφείαι",
      91
    ],
    [
      "Τεσενούφεως",
      90
    ],
    [
      "Μηδικοῦ Παρθικοῦ Σαρματικοῦ",
      90
    ],
    [
      "Θῶθ",
      90
    ],
    [
      "Τρύφων",
      90
    ],
    [
      "Πετρωνίου",
      90
    ],
    [
      "Κρονίων",
      90
    ],
    [
      "Παχων",
      90
    ],
    [
      "Δῖος",
      90
    ],
    [
      "Κορνηλίου",
      89
    ],
    [
      "Δημητρίῳ",
      88
    ],
    [
      "Μάξιμος",
      88
    ],
    [
      "Γεωργίῳ",
      88
    ],
    [
      "Δείου",
      88
    ],
    [
      "Πικῶτος",
      87
    ],
    [
      "Ναρμούθεως",
      87
    ],
    [
      "Βίκτωρος",
      87
    ],
    [
      "Πέρσου",
      86
    ],
    [
      "Βορρᾶ",
      86
    ],
    [
      "Θεοφίλου",
      85
    ],
    [
      "Διογένει",
      85
    ],
    [
      "Πακύσεως",
      84
    ],
    [
      "Παρεμβολῆς",
      84
    ],
    [
      "Πετεμενώφιος",
      84
    ],
    [
      "Διοσκόρῳ",
      84
    ],
    [
      "Αὐτοκράτορος Καίσαρος",
      84
    ],
    [
      "Μαρρῆς",
      84
    ],
    [
      "Στράτωνος",
      83
    ],
    [
      "Πόλεως",
      82
    ],
    [
      "Παποντῶς",
      82
    ],
    [
      "Μούχεως",
      82
    ],
    [
      "Σωτήριχος",
      82
    ],
    [
      "Πετεχῶντος",
      82
    ],
    [
      "Μεχειρ",
      82
    ],
    [
      "Πρωτάρχωι",
      82
    ],
    [
      "Τεβτύνει",
      81
    ],
    [
      "Γεροντίου",
      81
    ],
    [
      "Νήσων",
      81
    ],
    [
      "Φαωφι",
      81
    ],
    [
      "Θὼτ",
      81
    ],
    [
      "Καλλινίκου",
      81
    ],
    [
      "Σατύρου",
      81
    ],
    [
      "Σαράπιδι",
      80
    ],
    [
      "Μαρρείους",
      80
    ],
    [
      "Φατρήους",
      80
    ],
    [
      "Στέφανος",
      80
    ],
    [
      "Θατρῆτος",
      80
    ],
    [
      "Τιβερίου",
      80
    ],
    [
      "Σαμβᾶς",
      80
    ],
    [
      "Τεβτῦνιν",
      80
    ],
    [
      "Εὐδαιμονίδος",
      79
    ],
    [
      "Βουβάστου",
      79
    ],
    [
      "Σαβῖνος",
      79
    ],
    [
      "Ψάιτος",
      79
    ],
    [
      "Πετεμενῶφις",
      79
    ],
    [
      "Πεκυσίου",
      79
    ],
    [
      "Σιλβανὸς",
      78
    ],
    [
      "Λικιννίου Γαλλιηνοῦ Γερμανικοῦ",
      78
    ],
    [
      "Ποῦσι",
      78
    ],
    [
      "Τιμοθέου",
      78
    ],
    [
      "Ξανδικοῦ",
      78
    ],
    [
      "Πανεφρέμμεως",
      77
    ],
    [
      "Γερμανοῦ",
      77
    ],
    [
      "Δημητρίας",
      77
    ],
    [
      "Θερμούθιος",
      77
    ],
    [
      "Μεσορη",
      77
    ],
    [
      "Τεῶς",
      76
    ],
    [
      "Φλάουιος",
      76
    ],
    [
      "Γαίου Καίσαρος Σεβαστοῦ",
      76
    ],
    [
      "Εὐτυχοῦς Σεβαστοῦ",
      76
    ],
    [
      "Εὐημερίας",
      76
    ],
    [
      "Δωρίων",
      76
    ],
    [
      "Πτολεμαικοῦ",
      76
    ],
    [
      "Φίβιος",
      75
    ],
    [
      "Σαβεῖνος",
      75
    ],
    [
      "Θέωνα",
      75
    ],
    [
      "Πλῆνις",
      75
    ],
    [
      "Ζήνων",
      75
    ],
    [
      "Σώτου",
      75
    ],
    [
      "Θεὸν",
      74
    ],
    [
      "Σωτῆρος",
      74
    ],
    [
      "Ταμύσθας",
      73
    ],
    [
      "Αὐτοκράτορος Καίσαρος Πουπλίου",
      73
    ],
    [
      "Αἰγυπτίων",
      73
    ],
    [
      "Πρωτάρχου",
      73
    ],
    [
      "Φὶβ",
      73
    ],
    [
      "Εὐλογίου",
      73
    ],
    [
      "Παῆσις",
      73
    ],
    [
      "Πάτρωνος",
      73
    ],
    [
      "Φιλοθέου",
      73
    ],
    [
      "Χαιρήμονι",
      73
    ],
    [
      "Θύνεως",
      73
    ],
    [
      "Reprinted",
      73
    ],
    [
      "Πάπου",
      72
    ],
    [
      "Φίλων",
      72
    ],
    [
      "Εὐημερείας",
      72
    ],
    [
      "Πέτρῳ",
      72
    ],
    [
      "Φῖβ",
      72
    ],
    [
      "Αὐρηλίοις",
      71
    ],
    [
      "Φλαυίῳ",
      71
    ],
    [
      "Κλαυδιανοῦ",
      71
    ],
    [
      "Δανιὴλ",
      71
    ],
    [
      "Σωτὴρ",
      71
    ],
    [
      "Κυριακοῦ",
      71
    ],
    [
      "Φιλομητόρων",
      71
    ],
    [
      "Φιλόξενος",
      70
    ],
    [
      "Οὐαλέριος",
      70
    ],
    [
      "Εἰρήνης",
      70
    ],
    [
      "Διόδωρος",
      70
    ],
    [
      "Μύσθης",
      70
    ],
    [
      "Μακεδὼν",
      70
    ],
    [
      "Αὐρηλίᾳ",
      69
    ],
    [
      "Θαήσεως",
      69
    ],
    [
      "Αὐνῆς",
      69
    ],
    [
      "Σαβίνου",
      69
    ],
    [
      "Παύλῳ",
      69
    ],
    [
      "Διδύμη",
      69
    ],
    [
      "Χαιρήμωνος",
      69
    ],
    [
      "Δεῖος",
      69
    ],
    [
      "Εὐσεβοῦς Σεβαστοῦ",
      68
    ],
    [
      "Πετεχώνσιος",
      68
    ],
    [
      "Διονυ",
      68
    ],
    [
      "Λέοντος",
      68
    ],
    [
      "Αὐρήλιος Φοιβάμμων",
      68
    ],
    [
      "Κυρίου",
      67
    ],
    [
      "Φλαουΐου",
      67
    ],
    [
      "Εὐσεβοῦς",
      67
    ],
    [
      "Μαξιμίνου",
      67
    ],
    [
      "Βουσίρεως",
      67
    ],
    [
      "Λύκων",
      67
    ],
    [
      "Δίδυμον",
      67
    ],
    [
      "Εὐδαίμονι",
      66
    ],
    [
      "Κεφάλωνος",
      66
    ],
    [
      "Ταορσενούφεως",
      66
    ],
    [
      "Κοσμᾶς",
      66
    ],
    [
      "Παμοῦν",
      66
    ],
    [
      "Φιλα",
      66
    ],
    [
      "Αὐρήλιος Σαραπίων",
      66
    ],
    [
      "Φιλομήτορος",
      66
    ],
    [
      "Ταλεὶ",
      66
    ],
    [
      "Φρουρίου",
      65
    ],
    [
      "Πινουτίωνος",
      65
    ],
    [
      "Αὐτοκρατόρων",
      65
    ],
    [
      "Γερμανικείου",
      65
    ],
    [
      "Παμουθίου",
      65
    ],
    [
      "Φλαουίων",
      65
    ],
    [
      "Παρθικοῦ Μεγίστου",
      64
    ],
    [
      "Δομιτιανοῦ Καίσαρος",
      64
    ],
    [
      "Διονυσίας",
      64
    ],
    [
      "Οὐαλερίῳ",
      64
    ],
    [
      "Κερκεοσίρεως",
      64
    ],
    [
      "Κοπρῆς",
      64
    ],
    [
      "Γερμανὸς",
      64
    ],
    [
      "Κλαύδιος",
      64
    ],
    [
      "Φατρῆς",
      64
    ],
    [
      "Τάνεως",
      64
    ],
    [
      "Πλουτίωνος",
      64
    ],
    [
      "Φλαύιος",
      64
    ],
    [
      "Πέλα",
      64
    ],
    [
      "Οὐαλεριανοῦ",
      63
    ],
    [
      "Αὐρήλιος Σερῆνος",
      63
    ],
    [
      "Νεμεσίωνος",
      63
    ],
    [
      "Ψανσνῶς",
      63
    ],
    [
      "Ψενχώνσιος",
      63
    ],
    [
      "Πασήμιος",
      63
    ],
    [
      "Βερενίκης Εὐεργέτιδος",
      63
    ],
    [
      "Μαύρων",
      63
    ],
    [
      "Θεαδελφείᾳ",
      63
    ],
    [
      "Δημητρία",
      62
    ],
    [
      "Πακῦσις",
      62
    ],
    [
      "Εἰρηναίου",
      62
    ],
    [
      "Φαήριος",
      62
    ],
    [
      "Θερμουθαρίου",
      61
    ],
    [
      "Παθύρεως",
      61
    ],
    [
      "Βιθυνῶν",
      61
    ],
    [
      "Παχοῦμις",
      61
    ],
    [
      "Πετ",
      61
    ],
    [
      "Σισόις",
      61
    ],
    [
      "Λυσίμαχος",
      61
    ],
    [
      "Διοσκουρίδης",
      61
    ],
    [
      "Φίλιππος",
      61
    ],
    [
      "Τασουχαρίου",
      60
    ],
    [
      "Παήσιος",
      60
    ],
    [
      "Βίκτορι",
      60
    ],
    [
      "Ζαχαρίᾳ",
      60
    ],
    [
      "Κέφαλος",
      60
    ],
    [
      "Πετεμίνιος",
      60
    ],
    [
      "Φλαουίου Μαυρικίου Τιβερίου",
      60
    ],
    [
      "Δαμιανοῦ",
      60
    ],
    [
      "Παβοῦς",
      59
    ],
    [
      "Θεο",
      59
    ],
    [
      "Πανήμου",
      59
    ],
    [
      "Τακόνα",
      59
    ],
    [
      "Βησαρίωνος",
      59
    ],
    [
      "Εὐτύχου",
      59
    ],
    [
      "Σευήρου",
      59
    ],
    [
      "Σεμθέως",
      59
    ],
    [
      "Τεβτύνι",
      59
    ],
    [
      "Σεβαστοῦ Παῦνι",
      58
    ],
    [
      "Θαῆσις",
      58
    ],
    [
      "Δαίμων",
      58
    ],
    [
      "Δημη",
      58
    ],
    [
      "Φιλ",
      58
    ],
    [
      "Ψώβθεως",
      58
    ],
    [
      "Λύκου",
      58
    ],
    [
      "Βαβυλῶνος",
      58
    ],
    [
      "Πτολεμαίου Σωτῆρος",
      58
    ],
    [
      "Καρανίδα",
      57
    ],
    [
      "Τίτου Αἰλίου",
      57
    ],
    [
      "Γεμέλλου",
      57
    ],
    [
      "Κερκεσοῦχα",
      57
    ],
    [
      "Λεοντίου",
      57
    ],
    [
      "Παησίου",
      57
    ]
  ]
}